{
 "custom_fields": [
  {
   "_assign": null,
   "_comments": null,
   "_liked_by": null,
   "_user_tags": null,
   "allow_in_quick_entry": 0,
   "allow_on_submit": 0,
   "bold": 0,
   "collapsible": 0,
   "collapsible_depends_on": null,
   "columns": 0,
   "creation": "2023-01-09 11:40:27.371378",
   "default": null,
   "depends_on": null,
   "description": null,
   "docstatus": 0,
   "dt": "Rental Quotation",
   "fetch_from": null,
   "fetch_if_empty": 0,
   "fieldname": "departments",
   "fieldtype": "Select",
   "hidden": 0,
   "hide_border": 0,
   "hide_days": 0,
   "hide_seconds": 0,
   "idx": 26,
   "ignore_user_permissions": 0,
   "ignore_xss_filter": 0,
   "in_global_search": 0,
   "in_list_view": 0,
   "in_preview": 0,
   "in_standard_filter": 0,
   "insert_after": "sales_person",
   "label": "Departments",
   "length": 0,
   "mandatory_depends_on": null,
   "modified": "2022-02-28 10:26:56.560382",
   "modified_by": "Administrator",
   "name": "Rental Quotation-departments",
   "no_copy": 0,
   "non_negative": 0,
   "options": "\nTrading\nLogistics\nInspection\nRental\nAdmin\nMS - Sale\nMS - Repair\nMS - Internal\nQA/QC",
   "owner": "Administrator",
   "parent": null,
   "parentfield": null,
   "parenttype": null,
   "permlevel": 0,
   "precision": "",
   "print_hide": 0,
   "print_hide_if_no_value": 0,
   "print_width": null,
   "read_only": 0,
   "read_only_depends_on": null,
   "report_hide": 0,
   "reqd": 0,
   "search_index": 0,
   "translatable": 1,
   "unique": 0,
   "width": null
  },
  {
   "_assign": null,
   "_comments": null,
   "_liked_by": null,
   "_user_tags": null,
   "allow_in_quick_entry": 0,
   "allow_on_submit": 0,
   "bold": 0,
   "collapsible": 0,
   "collapsible_depends_on": null,
   "columns": 0,
   "creation": "2023-01-09 11:36:24.942976",
   "default": null,
   "depends_on": null,
   "description": null,
   "docstatus": 0,
   "dt": "Rental Quotation",
   "fetch_from": null,
   "fetch_if_empty": 0,
   "fieldname": "sales_person",
   "fieldtype": "Link",
   "hidden": 0,
   "hide_border": 0,
   "hide_days": 0,
   "hide_seconds": 0,
   "idx": 25,
   "ignore_user_permissions": 0,
   "ignore_xss_filter": 0,
   "in_global_search": 0,
   "in_list_view": 0,
   "in_preview": 0,
   "in_standard_filter": 0,
   "insert_after": "amended_from",
   "label": "Sales Person",
   "length": 0,
   "mandatory_depends_on": null,
   "modified": "2022-02-28 10:42:20.898140",
   "modified_by": "Administrator",
   "name": "Rental Quotation-sales_person",
   "no_copy": 0,
   "non_negative": 0,
   "options": "Sales Person",
   "owner": "Administrator",
   "parent": null,
   "parentfield": null,
   "parenttype": null,
   "permlevel": 0,
   "precision": "",
   "print_hide": 0,
   "print_hide_if_no_value": 0,
   "print_width": null,
   "read_only": 0,
   "read_only_depends_on": null,
   "report_hide": 0,
   "reqd": 0,
   "search_index": 0,
   "translatable": 0,
   "unique": 0,
   "width": null
  },
  {
   "_assign": null,
   "_comments": null,
   "_liked_by": null,
   "_user_tags": null,
   "allow_in_quick_entry": 0,
   "allow_on_submit": 0,
   "bold": 0,
   "collapsible": 0,
   "collapsible_depends_on": null,
   "columns": 0,
   "creation": "2023-01-13 16:50:25.916412",
   "default": null,
   "depends_on": null,
   "description": null,
   "docstatus": 0,
   "dt": "Rental Quotation",
   "fetch_from": null,
   "fetch_if_empty": 0,
   "fieldname": "opportunity",
   "fieldtype": "Link",
   "hidden": 0,
   "hide_border": 0,
   "hide_days": 0,
   "hide_seconds": 0,
   "idx": 22,
   "ignore_user_permissions": 0,
   "ignore_xss_filter": 0,
   "in_global_search": 0,
   "in_list_view": 0,
   "in_preview": 0,
   "in_standard_filter": 0,
   "insert_after": "column_break_16",
   "label": "Opportunity",
   "length": 0,
   "mandatory_depends_on": null,
   "modified": "2023-01-13 16:50:25.916412",
   "modified_by": "Administrator",
   "name": "Rental Quotation-opportunity",
   "no_copy": 0,
   "non_negative": 0,
   "options": "Opportunity",
   "owner": "Administrator",
   "parent": null,
   "parentfield": null,
   "parenttype": null,
   "permlevel": 0,
   "precision": "",
   "print_hide": 0,
   "print_hide_if_no_value": 0,
   "print_width": null,
   "read_only": 1,
   "read_only_depends_on": null,
   "report_hide": 0,
   "reqd": 0,
   "search_index": 0,
   "translatable": 0,
   "unique": 0,
   "width": null
  },
  {
   "_assign": null,
   "_comments": null,
   "_liked_by": null,
   "_user_tags": null,
   "allow_in_quick_entry": 0,
   "allow_on_submit": 0,
   "bold": 0,
   "collapsible": 0,
   "collapsible_depends_on": null,
   "columns": 0,
   "creation": "2023-01-14 10:23:20.003585",
   "default": null,
   "depends_on": null,
   "description": null,
   "docstatus": 0,
   "dt": "Rental Quotation",
   "fetch_from": null,
   "fetch_if_empty": 0,
   "fieldname": "customer_reference",
   "fieldtype": "Data",
   "hidden": 0,
   "hide_border": 0,
   "hide_days": 0,
   "hide_seconds": 0,
   "idx": 3,
   "ignore_user_permissions": 0,
   "ignore_xss_filter": 0,
   "in_global_search": 0,
   "in_list_view": 0,
   "in_preview": 0,
   "in_standard_filter": 0,
   "insert_after": "customer_name",
   "label": "Customer Reference",
   "length": 0,
   "mandatory_depends_on": null,
   "modified": "2023-01-14 10:23:20.003585",
   "modified_by": "Administrator",
   "name": "Rental Quotation-customer_reference",
   "no_copy": 0,
   "non_negative": 0,
   "options": null,
   "owner": "Administrator",
   "parent": null,
   "parentfield": null,
   "parenttype": null,
   "permlevel": 0,
   "precision": "",
   "print_hide": 0,
   "print_hide_if_no_value": 0,
   "print_width": null,
   "read_only": 0,
   "read_only_depends_on": null,
   "report_hide": 0,
   "reqd": 0,
   "search_index": 0,
   "translatable": 1,
   "unique": 0,
   "width": null
  },
  {
   "_assign": null,
   "_comments": null,
   "_liked_by": null,
   "_user_tags": null,
   "allow_in_quick_entry": 0,
   "allow_on_submit": 0,
   "bold": 0,
   "collapsible": 0,
   "collapsible_depends_on": null,
   "columns": 0,
   "creation": "2023-01-23 10:37:17.111546",
   "default": null,
   "depends_on": null,
   "description": null,
   "docstatus": 0,
   "dt": "Rental Quotation",
   "fetch_from": null,
   "fetch_if_empty": 0,
   "fieldname": "total_by_month",
   "fieldtype": "Float",
   "hidden": 1,
   "hide_border": 0,
   "hide_days": 0,
   "hide_seconds": 0,
   "idx": 14,
   "ignore_user_permissions": 0,
   "ignore_xss_filter": 0,
   "in_global_search": 0,
   "in_list_view": 0,
   "in_preview": 0,
   "in_standard_filter": 0,
   "insert_after": "items",
   "label": "Total by month",
   "length": 0,
   "mandatory_depends_on": null,
   "modified": "2023-01-23 10:37:17.111546",
   "modified_by": "Administrator",
   "name": "Rental Quotation-total_by_month",
   "no_copy": 0,
   "non_negative": 0,
   "options": null,
   "owner": "Administrator",
   "parent": null,
   "parentfield": null,
   "parenttype": null,
   "permlevel": 0,
   "precision": "",
   "print_hide": 0,
   "print_hide_if_no_value": 0,
   "print_width": null,
   "read_only": 0,
   "read_only_depends_on": null,
   "report_hide": 0,
   "reqd": 0,
   "search_index": 0,
   "translatable": 0,
   "unique": 0,
   "width": null
  }
 ],
 "custom_perms": [],
 "doctype": "Rental Quotation",
 "property_setters": [],
 "sync_on_migrate": 1
}